setup.py
tfidf/__init__.py
tfidf/tfidf.py
tfidf.egg-info/PKG-INFO
tfidf.egg-info/SOURCES.txt
tfidf.egg-info/dependency_links.txt
tfidf.egg-info/not-zip-safe
tfidf.egg-info/requires.txt
tfidf.egg-info/top_level.txt