Metadata-Version: 1.1
Name: tfidf
Version: 0.0.4
Summary: tfidf
Home-page: http://github.com/17zuoye/tfidf/
Author: David Chen
Author-email: mvjome@gmail.com
License: MIT
Platform: any
Classifier: Intended Audience :: Developers
Classifier: Operating System :: OS Independent
Classifier: Programming Language :: Python
Classifier: Topic :: Software Development :: Libraries :: Python Modules
